calculations/__init__.py
calculations/main.py
Calculations-1.10.dist-info/LICENSE
Calculations-1.10.dist-info/METADATA
Calculations-1.10.dist-info/WHEEL
Calculations-1.10.dist-info/top_level.txt
Calculations-1.10.dist-info/RECORD
